analyze_clarisse/__init__.py
analyze_clarisse/analyze.py
analyze_clarisse/param_check.py
analyze_clarisse/clarisse/analyze_worker_clarisse.exe
analyze_houdini/__init__.py
analyze_houdini/analyze.py
analyze_houdini/param_check.py
analyze_houdini/houdini/HoudiniAnalyze.pyd
analyze_houdini/houdini/HoudiniAnalyze_py310.pyd
analyze_houdini/houdini/HoudiniAnalyze_py311.pyd
analyze_houdini/houdini/HoudiniAnalyze_py312.pyd
analyze_houdini/houdini/HoudiniAnalyze_py37.pyd
analyze_houdini/houdini/HoudiniAnalyze_py39.pyd
analyze_houdini/houdini/run.py
analyze_maya/__init__.py
analyze_maya/analyze.py
analyze_maya/param_check.py
analyze_maya/maya/CommandLine.dll
analyze_maya/maya/Glob.dll
analyze_maya/maya/NLog.dll
analyze_maya/maya/Newtonsoft.Json.dll
analyze_maya/maya/OpenMcdf.dll
analyze_maya/maya/System.ValueTuple.dll
analyze_maya/maya/get_maya_infos.exe
analyze_maya/maya/maya_info.yaml
analyze_maya/maya/maya_warning.xml
analyze_maya/maya/template.txt
analyze_maya/maya/usdcat.exe
analyze_maya/maya/install/RenderG_plugin_submit.py
analyze_maya/maya/install/MayaInfo/MayaInfo.pyc
analyze_maya/maya/install/MayaInfo/__init__.pyc
analyze_maya/maya/install/MayaInfo/scene_files.pyc
analyze_maya/maya/install/MayaInfo/xgen_file.pyc
ascp/__init__.py
ascp/bin/Libssl-3-x64.dll
ascp/bin/afwsfeed.dll
ascp/bin/api-ms-win-core-file-l1-2-0.dll
ascp/bin/api-ms-win-core-file-l2-1-0.dll
ascp/bin/api-ms-win-core-localization-l1-2-0.dll
ascp/bin/api-ms-win-core-processthreads-l1-1-1.dll
ascp/bin/api-ms-win-core-synch-l1-2-0.dll
ascp/bin/api-ms-win-core-timezone-l1-1-0.dll
ascp/bin/api-ms-win-core-xstate-l2-1-0.dll
ascp/bin/api-ms-win-crt-conio-l1-1-0.dll
ascp/bin/api-ms-win-crt-convert-l1-1-0.dll
ascp/bin/api-ms-win-crt-environment-l1-1-0.dll
ascp/bin/api-ms-win-crt-filesystem-l1-1-0.dll
ascp/bin/api-ms-win-crt-heap-l1-1-0.dll
ascp/bin/api-ms-win-crt-locale-l1-1-0.dll
ascp/bin/api-ms-win-crt-math-l1-1-0.dll
ascp/bin/api-ms-win-crt-multibyte-l1-1-0.dll
ascp/bin/api-ms-win-crt-private-l1-1-0.dll
renderg_sdk-0.1.29.dist-info/METADATA
renderg_sdk-0.1.29.dist-info/WHEEL
renderg_sdk-0.1.29.dist-info/top_level.txt
renderg_sdk-0.1.29.dist-info/RECORD
