Metadata-Version: 2.1
Name: renderg-sdk
Version: 0.1.29
Summary: www.renderg.com
Home-page: https://github.com/renderg-repo/renderg-sdk.git
Author: RenderG
Author-email: support@renderg.com
Classifier: Programming Language :: Python
Classifier: Programming Language :: Python :: 2
Classifier: Programming Language :: Python :: 3
Requires-Dist: requests
Requires-Dist: tenacity
Requires-Dist: paho-mqtt
Requires-Dist: typing-extensions
